fastapi_llm/__init__.py
fastapi_llm/application.py
fastapi_llm/config.py
fastapi_llm/main.py
fastapi_llm/models.py
fastapi_llm/responses.py
fastapi_llm/router/__init__.py
fastapi_llm/router/chat.py
fastapi_llm/router/content.py
fastapi_llm/router/functions.py
fastapi_llm/router/knowledge.py
fastapi_llm/schema/__init__.py
fastapi_llm/schema/openai.py
fastapi_llm/schema/pinecone.py
fastapi_llm/schema/typedefs.py
fastapi_llm/service/__init__.py
fastapi_llm/service/auth.py
fastapi_llm/service/cloudflare.py
fastapi_llm/service/docker.py
fastapi_llm/service/faunadb/__init__.py
fastapi_llm/service/faunadb/client.py
fastapi_llm/service/faunadb/json.py
fastapi_llm/service/faunadb/lib/__init__.py
fastapi_llm/service/faunadb/lib/errors.py
fastapi_llm/service/faunadb/lib/objects.py
fastapi_llm/service/faunadb/lib/page.py
fastapi_llm/service/faunadb/lib/query.py
fastapi_llm/service/faunadb/odm.py
fastapi_llm/service/openai.py
fastapi_llm/service/pinecone.py
fastapi_llm/service/pubsub.py
fastapi_llm/ssr/__init__.py
fastapi_llm/ssr/formatters.py
fastapi_llm/ssr/ssr.py
fastapi_llm/tools/__init__.py
fastapi_llm/tools/email.py
fastapi_llm/tools/loaders.py
fastapi_llm/tools/search.py
fastapi_llm/tools/speech.py
fastapi_llm/utils.py
fastapi_llm-0.1.2.dist-info/METADATA
fastapi_llm-0.1.2.dist-info/WHEEL
fastapi_llm-0.1.2.dist-info/RECORD
