Metadata-Version: 2.1
Name: fastapi-llm
Version: 0.1.2
Summary: FastAPI for Large Language Models
Author: Oscar Bahamonde
Author-email: oscar.bahamonde@pucp.pe
Requires-Python: >=3.9,<4.0
Classifier: Programming Language :: Python :: 3
Classifier: Programming Language :: Python :: 3.9
Classifier: Programming Language :: Python :: 3.10
Classifier: Programming Language :: Python :: 3.11
Requires-Dist: aiohttp (>=3.8.5,<4.0.0)
Requires-Dist: aioredis (>=2.0.1,<3.0.0)
Requires-Dist: boto3 (>=1.28.26,<2.0.0)
Requires-Dist: bs4 (>=0.0.1,<0.0.2)
Requires-Dist: celery (>=5.3.1,<6.0.0)
Requires-Dist: fastapi (>=0.101.1,<0.102.0)
Requires-Dist: iso8601 (>=2.0.0,<3.0.0)
Requires-Dist: jinja2 (>=3.1.2,<4.0.0)
Requires-Dist: linkify (>=1.4,<2.0)
Requires-Dist: lxml (>=4.9.3,<5.0.0)
Requires-Dist: numpy (>=1.25.2,<2.0.0)
Requires-Dist: openai (>=0.27.8,<0.28.0)
Requires-Dist: pydantic (==1.10.2)
Requires-Dist: pypdf (>=3.15.1,<4.0.0)
Requires-Dist: python-multipart (>=0.0.6,<0.0.7)
Requires-Dist: redis (>=5.0.0,<6.0.0)
Requires-Dist: rich (>=13.5.2,<14.0.0)
Requires-Dist: tiktoken (>=0.4.0,<0.5.0)
Requires-Dist: uvicorn[standard] (>=0.23.2,<0.24.0)
